packet_trace/__init__.py
packet_trace/main.py
packet_trace-0.1.0.dist-info/entry_points.txt
packet_trace-0.1.0.dist-info/WHEEL
packet_trace-0.1.0.dist-info/METADATA
packet_trace-0.1.0.dist-info/RECORD
