Metadata-Version: 2.1
Name: packet-trace
Version: 0.1.0
Summary: A simple tool to trace packets as they pass through Linux netfilter.
Home-page: https://gitlab.com/python-utils2/packet_trace
Author: Mark Bools
Author-email: mark@saltyvagrant.com
Requires-Python: >=3.8,<4.0
Classifier: Development Status :: 3 - Alpha
Classifier: Environment :: Console
Classifier: Intended Audience :: Developers
Classifier: Intended Audience :: System Administrators
Classifier: Programming Language :: Python :: 3
Classifier: Programming Language :: Python :: 3.8
Classifier: Topic :: System :: Networking :: Firewalls
Classifier: Topic :: Utilities
Requires-Dist: libnetfilter (>=0.1.0,<0.2.0)
Requires-Dist: python-iptables (>=1.0.0,<2.0.0)
